vectorworks/__init__.py
vectorworks/auth.py
vectorworks/enums.py
vectorworks/index.py
vectorworks/retrievers/__init__.py
vectorworks/retrievers/generic.py
vectorworks/retrievers/pgvector.py
vectorworks/servers/vectorizer/__main__.py
vectorworks/servers/vectorizer/server.py
vectorworks/vectorizers/__init__.py
vectorworks/vectorizers/fasttext.py
vectorworks/vectorizers/generic.py
vectorworks/vectorizers/openai.py
vectorworks/vectorizers/remote.py
vectorworks/vectorizers/sbert.py
vectorworks/vectorizers/scikit.py
vectorworks-0.1.0.dist-info/LICENSE
vectorworks-0.1.0.dist-info/METADATA
vectorworks-0.1.0.dist-info/WHEEL
vectorworks-0.1.0.dist-info/top_level.txt
vectorworks-0.1.0.dist-info/RECORD
