Metadata-Version: 2.2
Name: vectorworks
Version: 0.1.0
Summary: Framework to procedurally query vector stores
Author: Rosaia B.V.
License: 
Project-URL: Repository, https://github.com/rosaia/vectorworks
Keywords: vectors,semantic text matching,document classification,RAG
Classifier: Development Status :: 4 - Beta
Classifier: License :: OSI Approved :: Apache Software License
Classifier: Programming Language :: Python :: 3
Classifier: Operating System :: OS Independent
Classifier: Topic :: Software Development :: Libraries
Requires-Python: >=3.10
License-File: LICENSE
Requires-Dist: numpy
Requires-Dist: pypeworks>=0.1.0
Requires-Dist: requests>=2.32.3
Requires-Dist: scikit-learn>=1.5.1
Requires-Dist: scipy>=1.14.0
Requires-Dist: sparse>=0.15.4
Provides-Extra: fasttext
Requires-Dist: fasttext>=0.9.3; extra == "fasttext"
Requires-Dist: compress-fasttext>=0.1.5; extra == "fasttext"
Provides-Extra: openai
Requires-Dist: openai>=1.65.0; extra == "openai"
Provides-Extra: pgvector
Requires-Dist: SQLAlchemy>=2.0.38; extra == "pgvector"
Provides-Extra: sbert
Requires-Dist: sentence-transformers>=3.3.0; extra == "sbert"
Provides-Extra: server
Requires-Dist: fastapi; extra == "server"
Requires-Dist: pydantic; extra == "server"
Requires-Dist: uvicorn; extra == "server"
